EmailTemplate.py
__init.py
EmailTemplate-0.0.3.dist-info/LICENSE
EmailTemplate-0.0.3.dist-info/METADATA
EmailTemplate-0.0.3.dist-info/WHEEL
EmailTemplate-0.0.3.dist-info/top_level.txt
EmailTemplate-0.0.3.dist-info/RECORD
