Metadata-Version: 2.1
Name: EmailTemplate
Version: 0.0.3
Summary: Email sending tempalte for begginers to send emails
Author-email: David Billingsley <daveandtaybillingsley@gmail.com>
Project-URL: Homepage, https://github.com/David-Billingsley/EmailTemplate
Project-URL: Issues, https://github.com/David-Billingsley/EmailTemplate/issues
Classifier: Programming Language :: Python :: 3
Classifier: License :: OSI Approved :: MIT License
Classifier: Operating System :: OS Independent
Requires-Python: >=3.8
License-File: LICENSE
